Voice_generator/VoiceProcessor.py
Voice_generator/__init__.py
openai_voicestream-0.1.2.dist-info/METADATA
openai_voicestream-0.1.2.dist-info/WHEEL
openai_voicestream-0.1.2.dist-info/top_level.txt
openai_voicestream-0.1.2.dist-info/RECORD
