Metadata-Version: 2.1
Name: openai_voicestream
Version: 0.1.2
Summary: A library for real-time text to speech processing using OpenAI API.
Home-page: https://github.com/kristofferv98/openai-voicestream.git
Author: Kristoffer Vatnehol
Author-email: kristoffer.vatnehol@gmail.com
License: MIT
Classifier: Programming Language :: Python :: 3
Classifier: License :: OSI Approved :: MIT License
Classifier: Operating System :: OS Independent
Requires-Python: >=3.6
Requires-Dist: pyaudio
Requires-Dist: httpx
Provides-Extra: dev
Requires-Dist: pytest ; extra == 'dev'
Requires-Dist: flake8 ; extra == 'dev'
